SanctionToolkit/__init__.py
SanctionToolkit/aes.py
SanctionToolkit/data_variators.py
SanctionToolkit/fake_firm_output.py
SanctionToolkit/join_firm_output.py
SanctionToolkit/reflist_preprocessor_consolidated.py
SanctionToolkit/reflist_profiler.py
SanctionToolkit/reflist_variator.py
SanctionToolkit/sanction_utility.py
SanctionToolkit/synthetic_data_creator_consolidated.py
SanctionToolkit/test_fake_output.py
SanctionToolkit/archived_modules/fincom_query.py
SanctionToolkit/archived_modules/sanction_run_faker.py
SanctionToolkit/archived_modules/sanction_visualizer.py
SanctionToolkit/config/__init__.py
SanctionToolkit/config/constants.py
SanctionToolkit/config/params.py
SanctionToolkit/reflist/combined_sanction_lists_20220505_main.csv
SanctionToolkit/resource/arabic_name_words.txt
SanctionToolkit/resource/chinese_name_words.txt
SanctionToolkit/resource/company_aux_words.txt
SanctionToolkit/resource/company_common_words.txt
SanctionToolkit/resource/company_names.txt
SanctionToolkit/resource/fake_name_list.txt
SanctionToolkit/resource/firstname_synonyms.txt
SanctionToolkit/resource/firstnames.txt
SanctionToolkit/resource/lastnames.txt
SanctionToolkit/resource/name_paranthesis.txt
SanctionToolkit/resource/russian_name_words.txt
SanctionToolkit/resource/titles.txt
SanctionToolkit/russian_names/__init__.py
SanctionToolkit/russian_names/_data.zip
SanctionToolkit/russian_names/consts.py
SanctionToolkit/russian_names/names.py
SanctionToolkit/russian_names/utils.py
SanctionToolkit-0.1.dist-info/LICENCE.txt
SanctionToolkit-0.1.dist-info/METADATA
SanctionToolkit-0.1.dist-info/WHEEL
SanctionToolkit-0.1.dist-info/top_level.txt
SanctionToolkit-0.1.dist-info/RECORD
