Metadata-Version: 2.1
Name: SanctionToolkit
Version: 0.1
Summary: Sanction Screning Synthetic Test Data Generator
Home-page: UNKNOWN
Author: Bunyamin DURSUN
Author-email: Bunyamin.Dursun@fca.org.uk
License: FCA Licence
Platform: UNKNOWN
License-File: LICENCE.txt
